[
  {
    "model": "auth.user",
    "pk": 2,
    "fields": {
      "username": "volkswagoncampfire",
      "password": "bHeaYOXhWoim571rlck20m5ycoKhmBec",
      "email": "volkswagoncampfire@email.com",
      "is_superuser": false,
      "is_staff": false,
      "is_active": true,
      "date_joined": "1970-01-01 12:00:00.0+00:00"
    }
  },
  {
    "model": "auth.user",
    "pk": 3,
    "fields": {
      "username": "pulsesmonument",
      "password": "tQLqSQ7ZyOEIOTdduXlNTYQUSrL53fcb",
      "email": "pulsesmonument@email.com",
      "is_superuser": false,
      "is_staff": false,
      "is_active": true,
      "date_joined": "1970-01-01 12:00:00.0+00:00"
    }
  },
  {
    "model": "auth.user",
    "pk": 4,
    "fields": {
      "username": "featherguidance",
      "password": "wmjhz7LYWc3eaZGaWczGxroXBmqhAegT",
      "email": "featherguidance@email.com",
      "is_superuser": false,
      "is_staff": false,
      "is_active": true,
      "date_joined": "1970-01-01 12:00:00.0+00:00"
    }
  },
  {
    "model": "auth.user",
    "pk": 5,
    "fields": {
      "username": "trivialloser",
      "password": "6PUgFtIMQWuzoZDsoUZJD8tdoz9aKyQm",
      "email": "trivialloser@email.com",
      "is_superuser": false,
      "is_staff": false,
      "is_active": true,
      "date_joined": "1970-01-01 12:00:00.0+00:00"
    }
  },
  {
    "model": "auth.user",
    "pk": 6,
    "fields": {
      "username": "fairlyknowledge",
      "password": "c22OFq6HKq9sGNOrg3baCK66JAyKtS50",
      "email": "fairlyknowledge@email.com",
      "is_superuser": false,
      "is_staff": false,
      "is_active": true,
      "date_joined": "1970-01-01 12:00:00.0+00:00"
    }
  },
  {
    "model": "auth.user",
    "pk": 7,
    "fields": {
      "username": "lazymurmur",
      "password": "bsH5DiFSj2HqtyYfPr4HxFOtocJNnOuh",
      "email": "lazymurmur@email.com",
      "is_superuser": false,
      "is_staff": false,
      "is_active": true,
      "date_joined": "1970-01-01 12:00:00.0+00:00"
    }
  },
  {
    "model": "auth.user",
    "pk": 8,
    "fields": {
      "username": "pufferfishprefer",
      "password": "mQ4ZbdXGYIucl8iucq1PjmSZR5669IE1",
      "email": "pufferfishprefer@email.com",
      "is_superuser": false,
      "is_staff": false,
      "is_active": true,
      "date_joined": "1970-01-01 12:00:00.0+00:00"
    }
  },
  {
    "model": "auth.user",
    "pk": 9,
    "fields": {
      "username": "sowirritable",
      "password": "fuDJLbps1vLlOBQwVR6nAlH9tgwZtfn5",
      "email": "sowirritable@email.com",
      "is_superuser": false,
      "is_staff": false,
      "is_active": true,
      "date_joined": "1970-01-01 12:00:00.0+00:00"
    }
  },
  {
    "model": "auth.user",
    "pk": 10,
    "fields": {
      "username": "lapwingmourner",
      "password": "3OhX5HhMs3JS35O6QEhyhKrwst368weG",
      "email": "lapwingmourner@email.com",
      "is_superuser": false,
      "is_staff": false,
      "is_active": true,
      "date_joined": "1970-01-01 12:00:00.0+00:00"
    }
  },
  {
    "model": "auth.user",
    "pk": 11,
    "fields": {
      "username": "slipwaynorth",
      "password": "K4XavlEMkCGlM3FYNrg24onE8cQp8Y4j",
      "email": "slipwaynorth@email.com",
      "is_superuser": false,
      "is_staff": false,
      "is_active": true,
      "date_joined": "1970-01-01 12:00:00.0+00:00"
    }
  },
  {
    "model": "auth.user",
    "pk": 12,
    "fields": {
      "username": "zonkedgod",
      "password": "GcfjTyWb6lZf6DIEF9LAXmB97yj2SlIg",
      "email": "zonkedgod@email.com",
      "is_superuser": false,
      "is_staff": false,
      "is_active": true,
      "date_joined": "1970-01-01 12:00:00.0+00:00"
    }
  },
  {
    "model": "auth.user",
    "pk": 13,
    "fields": {
      "username": "cabbagebazaar",
      "password": "TkiMcGmZfrnG8xJe8NBhSHg0CkUrKGKO",
      "email": "cabbagebazaar@email.com",
      "is_superuser": false,
      "is_staff": false,
      "is_active": true,
      "date_joined": "1970-01-01 12:00:00.0+00:00"
    }
  },
  {
    "model": "auth.user",
    "pk": 14,
    "fields": {
      "username": "heyruddy",
      "password": "sNWV36OnlsuLF5nBC8UaYI78wNRgeWKf",
      "email": "heyruddy@email.com",
      "is_superuser": false,
      "is_staff": false,
      "is_active": true,
      "date_joined": "1970-01-01 12:00:00.0+00:00"
    }
  },
  {
    "model": "auth.user",
    "pk": 15,
    "fields": {
      "username": "ramwonder",
      "password": "63E7N7KIDdjiyaXc7bnPV3ilBNvYpdU8",
      "email": "ramwonder@email.com",
      "is_superuser": false,
      "is_staff": false,
      "is_active": true,
      "date_joined": "1970-01-01 12:00:00.0+00:00"
    }
  },
  {
    "model": "auth.user",
    "pk": 16,
    "fields": {
      "username": "dietnumeral",
      "password": "DHJHJgwQzASRbTUsKITMJLeSL52Wntgh",
      "email": "dietnumeral@email.com",
      "is_superuser": false,
      "is_staff": false,
      "is_active": true,
      "date_joined": "1970-01-01 12:00:00.0+00:00"
    }
  },
  {
    "model": "auth.user",
    "pk": 17,
    "fields": {
      "username": "cowardlyphysicist",
      "password": "8yNBxKzR6bVXDrTVPLuCAqKI2K9jwbUj",
      "email": "cowardlyphysicist@email.com",
      "is_superuser": false,
      "is_staff": false,
      "is_active": true,
      "date_joined": "1970-01-01 12:00:00.0+00:00"
    }
  },
  {
    "model": "auth.user",
    "pk": 18,
    "fields": {
      "username": "strippedanywhere",
      "password": "TdzExUTyV9TQKXPq6VR6IVNNuAEQeT58",
      "email": "strippedanywhere@email.com",
      "is_superuser": false,
      "is_staff": false,
      "is_active": true,
      "date_joined": "1970-01-01 12:00:00.0+00:00"
    }
  },
  {
    "model": "auth.user",
    "pk": 19,
    "fields": {
      "username": "deceivepermanent",
      "password": "oBwDU2Fy4XuGYwaGFkWpUU3pPSdhhJEE",
      "email": "deceivepermanent@email.com",
      "is_superuser": false,
      "is_staff": false,
      "is_active": true,
      "date_joined": "1970-01-01 12:00:00.0+00:00"
    }
  },
  {
    "model": "auth.user",
    "pk": 20,
    "fields": {
      "username": "apronvirtually",
      "password": "3TLO6ys2v4lfRs6DXdJkfw7gjbu8rrkn",
      "email": "apronvirtually@email.com",
      "is_superuser": false,
      "is_staff": false,
      "is_active": true,
      "date_joined": "1970-01-01 12:00:00.0+00:00"
    }
  },
  {
    "model": "auth.user",
    "pk": 21,
    "fields": {
      "username": "loosenebulous",
      "password": "5SOZQ5pJGh55WLs2IA0uEhBr8JYNTHC8",
      "email": "loosenebulous@email.com",
      "is_superuser": false,
      "is_staff": false,
      "is_active": true,
      "date_joined": "1970-01-01 12:00:00.0+00:00"
    }
  },
  {
    "model": "auth.user",
    "pk": 22,
    "fields": {
      "username": "frostsquish",
      "password": "gnydToSQvOCIcTCFDzXCK7RtwGYhgK3b",
      "email": "frostsquish@email.com",
      "is_superuser": false,
      "is_staff": false,
      "is_active": true,
      "date_joined": "1970-01-01 12:00:00.0+00:00"
    }
  },
  {
    "model": "auth.user",
    "pk": 23,
    "fields": {
      "username": "listenertweet",
      "password": "e3fTDVltKBNcgwROm0TkXqehKL9cMjZ6",
      "email": "listenertweet@email.com",
      "is_superuser": false,
      "is_staff": false,
      "is_active": true,
      "date_joined": "1970-01-01 12:00:00.0+00:00"
    }
  },
  {
    "model": "auth.user",
    "pk": 24,
    "fields": {
      "username": "examplebuntline",
      "password": "Cpw8aDd3dqYMTUZGSw6lH7fP2nq06BJa",
      "email": "examplebuntline@email.com",
      "is_superuser": false,
      "is_staff": false,
      "is_active": true,
      "date_joined": "1970-01-01 12:00:00.0+00:00"
    }
  },
  {
    "model": "auth.user",
    "pk": 25,
    "fields": {
      "username": "handkerchiefmouth",
      "password": "k13UYbFmdvyTfAwwXm3iBFKPUt3SVqd1",
      "email": "handkerchiefmouth@email.com",
      "is_superuser": false,
      "is_staff": false,
      "is_active": true,
      "date_joined": "1970-01-01 12:00:00.0+00:00"
    }
  },
  {
    "model": "auth.user",
    "pk": 26,
    "fields": {
      "username": "meetingarab",
      "password": "0O0BxRAVdfouEREmwb1f04xzeDAh3dr5",
      "email": "meetingarab@email.com",
      "is_superuser": false,
      "is_staff": false,
      "is_active": true,
      "date_joined": "1970-01-01 12:00:00.0+00:00"
    }
  },
  {
    "model": "auth.user",
    "pk": 27,
    "fields": {
      "username": "trafalgarjukebox",
      "password": "8IzOYXFdROf7xqWnYF7ZBEblZtQFmc9P",
      "email": "trafalgarjukebox@email.com",
      "is_superuser": false,
      "is_staff": false,
      "is_active": true,
      "date_joined": "1970-01-01 12:00:00.0+00:00"
    }
  },
  {
    "model": "auth.user",
    "pk": 28,
    "fields": {
      "username": "totemweepy",
      "password": "uVIT0HtZCE9WVpHz0RLe0GV08o93y6eS",
      "email": "totemweepy@email.com",
      "is_superuser": false,
      "is_staff": false,
      "is_active": true,
      "date_joined": "1970-01-01 12:00:00.0+00:00"
    }
  },
  {
    "model": "auth.user",
    "pk": 29,
    "fields": {
      "username": "assroach",
      "password": "UWw8nYiSQZq9LfZzO7WWE4pKPL3rYkL3",
      "email": "assroach@email.com",
      "is_superuser": false,
      "is_staff": false,
      "is_active": true,
      "date_joined": "1970-01-01 12:00:00.0+00:00"
    }
  },
  {
    "model": "auth.user",
    "pk": 30,
    "fields": {
      "username": "scallopssteady",
      "password": "86mWxhy0TUBhuMhxsF2DvByPUYuoF7RL",
      "email": "scallopssteady@email.com",
      "is_superuser": false,
      "is_staff": false,
      "is_active": true,
      "date_joined": "1970-01-01 12:00:00.0+00:00"
    }
  },
  {
    "model": "auth.user",
    "pk": 31,
    "fields": {
      "username": "dumbasscrocodile",
      "password": "AKTrg2gi1AJ5vLzQvTxc2ZHPjRYYFz5M",
      "email": "dumbasscrocodile@email.com",
      "is_superuser": false,
      "is_staff": false,
      "is_active": true,
      "date_joined": "1970-01-01 12:00:00.0+00:00"
    }
  },
  {
    "model": "auth.user",
    "pk": 32,
    "fields": {
      "username": "biddynervous",
      "password": "HIE8bb8xDhKjroJqPli1VfEyortHPcKB",
      "email": "biddynervous@email.com",
      "is_superuser": false,
      "is_staff": false,
      "is_active": true,
      "date_joined": "1970-01-01 12:00:00.0+00:00"
    }
  },
  {
    "model": "auth.user",
    "pk": 33,
    "fields": {
      "username": "birchwoodorchestra",
      "password": "H2mJTyDGT0xOGIN0jpdX4i0RWVSQLZSX",
      "email": "birchwoodorchestra@email.com",
      "is_superuser": false,
      "is_staff": false,
      "is_active": true,
      "date_joined": "1970-01-01 12:00:00.0+00:00"
    }
  },
  {
    "model": "auth.user",
    "pk": 34,
    "fields": {
      "username": "safetywelcome",
      "password": "2HP51XL5kKN6B1wYvPK3v1mp4K9Z5hpO",
      "email": "safetywelcome@email.com",
      "is_superuser": false,
      "is_staff": false,
      "is_active": true,
      "date_joined": "1970-01-01 12:00:00.0+00:00"
    }
  },
  {
    "model": "auth.user",
    "pk": 35,
    "fields": {
      "username": "duckafrican",
      "password": "6SD7RDyCJzCjyAkkYqj65SNPeGho6E6f",
      "email": "duckafrican@email.com",
      "is_superuser": false,
      "is_staff": false,
      "is_active": true,
      "date_joined": "1970-01-01 12:00:00.0+00:00"
    }
  },
  {
    "model": "auth.user",
    "pk": 36,
    "fields": {
      "username": "bidisle",
      "password": "RdVcSXrS8WStVSCFRwM2J8kFg8JkXkJA",
      "email": "bidisle@email.com",
      "is_superuser": false,
      "is_staff": false,
      "is_active": true,
      "date_joined": "1970-01-01 12:00:00.0+00:00"
    }
  },
  {
    "model": "auth.user",
    "pk": 37,
    "fields": {
      "username": "porcupinedramatic",
      "password": "7bQlMSG5b08zoFWn9nCH7bAzFKxOiCMM",
      "email": "porcupinedramatic@email.com",
      "is_superuser": false,
      "is_staff": false,
      "is_active": true,
      "date_joined": "1970-01-01 12:00:00.0+00:00"
    }
  },
  {
    "model": "auth.user",
    "pk": 38,
    "fields": {
      "username": "toothchannel",
      "password": "9ZIT4H4RtMyBCuAtkGUW5iKJA949aBgp",
      "email": "toothchannel@email.com",
      "is_superuser": false,
      "is_staff": false,
      "is_active": true,
      "date_joined": "1970-01-01 12:00:00.0+00:00"
    }
  },
  {
    "model": "auth.user",
    "pk": 39,
    "fields": {
      "username": "duskyrare",
      "password": "c6520DPqbFziCEK1bDVeB2GoGL1ECIVL",
      "email": "duskyrare@email.com",
      "is_superuser": false,
      "is_staff": false,
      "is_active": true,
      "date_joined": "1970-01-01 12:00:00.0+00:00"
    }
  },
  {
    "model": "auth.user",
    "pk": 40,
    "fields": {
      "username": "raftingmidlands",
      "password": "e84wKc0KPfIJMnz1G3h5I9ExO42QhEfC",
      "email": "raftingmidlands@email.com",
      "is_superuser": false,
      "is_staff": false,
      "is_active": true,
      "date_joined": "1970-01-01 12:00:00.0+00:00"
    }
  },
  {
    "model": "auth.user",
    "pk": 41,
    "fields": {
      "username": "soberideal",
      "password": "vvQTx26IN5oLQoLeJPtPVJUNiRiIvbci",
      "email": "soberideal@email.com",
      "is_superuser": false,
      "is_staff": false,
      "is_active": true,
      "date_joined": "1970-01-01 12:00:00.0+00:00"
    }
  },
  {
    "model": "auth.user",
    "pk": 42,
    "fields": {
      "username": "crushupbeat",
      "password": "Z2ZhltTqcW92YoCwDiyHPaYrKkMs41k9",
      "email": "crushupbeat@email.com",
      "is_superuser": false,
      "is_staff": false,
      "is_active": true,
      "date_joined": "1970-01-01 12:00:00.0+00:00"
    }
  },
  {
    "model": "auth.user",
    "pk": 43,
    "fields": {
      "username": "observerwood",
      "password": "kjGpuEhson70jttk5S9yrO7TKHCc0ZFP",
      "email": "observerwood@email.com",
      "is_superuser": false,
      "is_staff": false,
      "is_active": true,
      "date_joined": "1970-01-01 12:00:00.0+00:00"
    }
  },
  {
    "model": "auth.user",
    "pk": 44,
    "fields": {
      "username": "cookietaurus",
      "password": "zbPSWBo5I0I9Axt1YWtKGxCGmLZdI258",
      "email": "cookietaurus@email.com",
      "is_superuser": false,
      "is_staff": false,
      "is_active": true,
      "date_joined": "1970-01-01 12:00:00.0+00:00"
    }
  },
  {
    "model": "auth.user",
    "pk": 45,
    "fields": {
      "username": "molarhesitant",
      "password": "fgTYdSW7p2FhEV2e5jNOp4H4mNIpj0FF",
      "email": "molarhesitant@email.com",
      "is_superuser": false,
      "is_staff": false,
      "is_active": true,
      "date_joined": "1970-01-01 12:00:00.0+00:00"
    }
  },
  {
    "model": "auth.user",
    "pk": 46,
    "fields": {
      "username": "cheeseburgerstatistics",
      "password": "X1Zw9NeKdwJWKdLD3zUp2mXNuoHuf72c",
      "email": "cheeseburgerstatistics@email.com",
      "is_superuser": false,
      "is_staff": false,
      "is_active": true,
      "date_joined": "1970-01-01 12:00:00.0+00:00"
    }
  },
  {
    "model": "auth.user",
    "pk": 47,
    "fields": {
      "username": "thrusheparrot",
      "password": "ruDOUDQMmF6jEWgKaNFIaC0gcPpD1YIO",
      "email": "thrusheparrot@email.com",
      "is_superuser": false,
      "is_staff": false,
      "is_active": true,
      "date_joined": "1970-01-01 12:00:00.0+00:00"
    }
  },
  {
    "model": "auth.user",
    "pk": 48,
    "fields": {
      "username": "lobejibe",
      "password": "LkZVEKmtdV3YeA66Caiy3fCLngEGt5JR",
      "email": "lobejibe@email.com",
      "is_superuser": false,
      "is_staff": false,
      "is_active": true,
      "date_joined": "1970-01-01 12:00:00.0+00:00"
    }
  },
  {
    "model": "auth.user",
    "pk": 49,
    "fields": {
      "username": "wateryexecutive",
      "password": "TvNkpWy17RQyKzTX3bj26HJ31VGxeS20",
      "email": "wateryexecutive@email.com",
      "is_superuser": false,
      "is_staff": false,
      "is_active": true,
      "date_joined": "1970-01-01 12:00:00.0+00:00"
    }
  },
  {
    "model": "auth.user",
    "pk": 50,
    "fields": {
      "username": "boughtjuices",
      "password": "LDxi9N6RqYs0fwmclHKx4a5kT92i1Pjk",
      "email": "boughtjuices@email.com",
      "is_superuser": false,
      "is_staff": false,
      "is_active": true,
      "date_joined": "1970-01-01 12:00:00.0+00:00"
    }
  },
  {
    "model": "auth.user",
    "pk": 51,
    "fields": {
      "username": "lineardeadwood",
      "password": "0yBKWDbpVLMxciG7Pf7a3LKhf0NxpZsH",
      "email": "lineardeadwood@email.com",
      "is_superuser": false,
      "is_staff": false,
      "is_active": true,
      "date_joined": "1970-01-01 12:00:00.0+00:00"
    }
  },
  {
    "model": "auth.user",
    "pk": 52,
    "fields": {
      "username": "ensureboatswain",
      "password": "su4QKfrRnGyuHjHGlv78VA184V1k0ntG",
      "email": "ensureboatswain@email.com",
      "is_superuser": false,
      "is_staff": false,
      "is_active": true,
      "date_joined": "1970-01-01 12:00:00.0+00:00"
    }
  },
  {
    "model": "auth.user",
    "pk": 53,
    "fields": {
      "username": "awarenessmakeshift",
      "password": "59vv09K2EbTi4RgwqwnzuVGfcIyYbsAn",
      "email": "awarenessmakeshift@email.com",
      "is_superuser": false,
      "is_staff": false,
      "is_active": true,
      "date_joined": "1970-01-01 12:00:00.0+00:00"
    }
  },
  {
    "model": "auth.user",
    "pk": 54,
    "fields": {
      "username": "simplybasic",
      "password": "NFITfaZKn4KaZcTIAblSpQ0sLslyZCkX",
      "email": "simplybasic@email.com",
      "is_superuser": false,
      "is_staff": false,
      "is_active": true,
      "date_joined": "1970-01-01 12:00:00.0+00:00"
    }
  },
  {
    "model": "auth.user",
    "pk": 55,
    "fields": {
      "username": "affirmreceipt",
      "password": "aOJAhkdluHLmzqnrgUyvzUoY2tXP8Jl5",
      "email": "affirmreceipt@email.com",
      "is_superuser": false,
      "is_staff": false,
      "is_active": true,
      "date_joined": "1970-01-01 12:00:00.0+00:00"
    }
  },
  {
    "model": "auth.user",
    "pk": 56,
    "fields": {
      "username": "hooliganpiano",
      "password": "tlppepUA3LMF8HjSu2GI9h4ZBCEtsbwR",
      "email": "hooliganpiano@email.com",
      "is_superuser": false,
      "is_staff": false,
      "is_active": true,
      "date_joined": "1970-01-01 12:00:00.0+00:00"
    }
  },
  {
    "model": "auth.user",
    "pk": 57,
    "fields": {
      "username": "candidwrist",
      "password": "NTTsOyY6bzpGm5LbRbQbYRUrKPVUFQLz",
      "email": "candidwrist@email.com",
      "is_superuser": false,
      "is_staff": false,
      "is_active": true,
      "date_joined": "1970-01-01 12:00:00.0+00:00"
    }
  },
  {
    "model": "auth.user",
    "pk": 58,
    "fields": {
      "username": "stunningominous",
      "password": "xXt5CaYAS3g3R9vZYAw5kMwd8mC5UcEa",
      "email": "stunningominous@email.com",
      "is_superuser": false,
      "is_staff": false,
      "is_active": true,
      "date_joined": "1970-01-01 12:00:00.0+00:00"
    }
  },
  {
    "model": "auth.user",
    "pk": 59,
    "fields": {
      "username": "righttourist",
      "password": "CfnmEfumin8cI7u6H3nnkfkC770IqETz",
      "email": "righttourist@email.com",
      "is_superuser": false,
      "is_staff": false,
      "is_active": true,
      "date_joined": "1970-01-01 12:00:00.0+00:00"
    }
  },
  {
    "model": "auth.user",
    "pk": 60,
    "fields": {
      "username": "airportcolony",
      "password": "T6ITDR1loRospiHybP0QKdGDj8YgCcZ1",
      "email": "airportcolony@email.com",
      "is_superuser": false,
      "is_staff": false,
      "is_active": true,
      "date_joined": "1970-01-01 12:00:00.0+00:00"
    }
  },
  {
    "model": "auth.user",
    "pk": 61,
    "fields": {
      "username": "letovercoat",
      "password": "2vsfUjoXr1we1OYD1FSnMxABGQVW8tEi",
      "email": "letovercoat@email.com",
      "is_superuser": false,
      "is_staff": false,
      "is_active": true,
      "date_joined": "1970-01-01 12:00:00.0+00:00"
    }
  },
  {
    "model": "auth.user",
    "pk": 62,
    "fields": {
      "username": "catfishmagnet",
      "password": "kRvj2uvFMtOwb9Cee0MRKg2UBlY6C7nu",
      "email": "catfishmagnet@email.com",
      "is_superuser": false,
      "is_staff": false,
      "is_active": true,
      "date_joined": "1970-01-01 12:00:00.0+00:00"
    }
  },
  {
    "model": "auth.user",
    "pk": 63,
    "fields": {
      "username": "basefrankfurter",
      "password": "VbP7596tuqptfZ7HJrAQ8ozY0Lqgloja",
      "email": "basefrankfurter@email.com",
      "is_superuser": false,
      "is_staff": false,
      "is_active": true,
      "date_joined": "1970-01-01 12:00:00.0+00:00"
    }
  },
  {
    "model": "auth.user",
    "pk": 64,
    "fields": {
      "username": "chucklesari",
      "password": "AdO4JszQtUhxgfkPtST9AujdaOUDQw4m",
      "email": "chucklesari@email.com",
      "is_superuser": false,
      "is_staff": false,
      "is_active": true,
      "date_joined": "1970-01-01 12:00:00.0+00:00"
    }
  },
  {
    "model": "auth.user",
    "pk": 65,
    "fields": {
      "username": "watchfulmorose",
      "password": "VgkJKwUJD4JKbcpU35NqWG82cECuctV4",
      "email": "watchfulmorose@email.com",
      "is_superuser": false,
      "is_staff": false,
      "is_active": true,
      "date_joined": "1970-01-01 12:00:00.0+00:00"
    }
  },
  {
    "model": "auth.user",
    "pk": 66,
    "fields": {
      "username": "newequally",
      "password": "E1gxGftGhhESBQQfJR2K127XbyW0XviC",
      "email": "newequally@email.com",
      "is_superuser": false,
      "is_staff": false,
      "is_active": true,
      "date_joined": "1970-01-01 12:00:00.0+00:00"
    }
  },
  {
    "model": "auth.user",
    "pk": 67,
    "fields": {
      "username": "demureactress",
      "password": "3KaT4uKvv1RiyDobN4zbKSupFPl6t8q7",
      "email": "demureactress@email.com",
      "is_superuser": false,
      "is_staff": false,
      "is_active": true,
      "date_joined": "1970-01-01 12:00:00.0+00:00"
    }
  },
  {
    "model": "auth.user",
    "pk": 68,
    "fields": {
      "username": "wavyhousing",
      "password": "AqgqEmudbKXuHTU9pzRwNIRIEHNVSlNh",
      "email": "wavyhousing@email.com",
      "is_superuser": false,
      "is_staff": false,
      "is_active": true,
      "date_joined": "1970-01-01 12:00:00.0+00:00"
    }
  },
  {
    "model": "auth.user",
    "pk": 69,
    "fields": {
      "username": "pharmacisttheme",
      "password": "xqQPqp1YYXUJSvm5fSyTGWpPhLztmkOB",
      "email": "pharmacisttheme@email.com",
      "is_superuser": false,
      "is_staff": false,
      "is_active": true,
      "date_joined": "1970-01-01 12:00:00.0+00:00"
    }
  },
  {
    "model": "auth.user",
    "pk": 70,
    "fields": {
      "username": "medullahandkerchief",
      "password": "OQEhb6CFvR4K54hhJpaZJoo3e2FFJUiq",
      "email": "medullahandkerchief@email.com",
      "is_superuser": false,
      "is_staff": false,
      "is_active": true,
      "date_joined": "1970-01-01 12:00:00.0+00:00"
    }
  },
  {
    "model": "auth.user",
    "pk": 71,
    "fields": {
      "username": "commissionprohibited",
      "password": "EoJUOEDF8T1UpRBeyOZSerhVSUQm4g8G",
      "email": "commissionprohibited@email.com",
      "is_superuser": false,
      "is_staff": false,
      "is_active": true,
      "date_joined": "1970-01-01 12:00:00.0+00:00"
    }
  },
  {
    "model": "auth.user",
    "pk": 72,
    "fields": {
      "username": "fuelwelsh",
      "password": "kB1XVVgYOGaxxPSUrNssWwSqf4QTVppi",
      "email": "fuelwelsh@email.com",
      "is_superuser": false,
      "is_staff": false,
      "is_active": true,
      "date_joined": "1970-01-01 12:00:00.0+00:00"
    }
  },
  {
    "model": "auth.user",
    "pk": 73,
    "fields": {
      "username": "ceremoniouspoem",
      "password": "N6hEWiRLAFLgwb3i1prxos8snMcvHIw1",
      "email": "ceremoniouspoem@email.com",
      "is_superuser": false,
      "is_staff": false,
      "is_active": true,
      "date_joined": "1970-01-01 12:00:00.0+00:00"
    }
  },
  {
    "model": "auth.user",
    "pk": 74,
    "fields": {
      "username": "phaseknickers",
      "password": "fLBnN1njEFUeYE0BfBQRxYRbNtyybNq0",
      "email": "phaseknickers@email.com",
      "is_superuser": false,
      "is_staff": false,
      "is_active": true,
      "date_joined": "1970-01-01 12:00:00.0+00:00"
    }
  },
  {
    "model": "auth.user",
    "pk": 75,
    "fields": {
      "username": "heroacross",
      "password": "XArjYayDLIn2QM64xaik9wB7djPPRIpx",
      "email": "heroacross@email.com",
      "is_superuser": false,
      "is_staff": false,
      "is_active": true,
      "date_joined": "1970-01-01 12:00:00.0+00:00"
    }
  },
  {
    "model": "auth.user",
    "pk": 76,
    "fields": {
      "username": "insistenttobacco",
      "password": "ZMTSB3BlKfHxCCbBm4KS6a7dRbZc7h5G",
      "email": "insistenttobacco@email.com",
      "is_superuser": false,
      "is_staff": false,
      "is_active": true,
      "date_joined": "1970-01-01 12:00:00.0+00:00"
    }
  },
  {
    "model": "auth.user",
    "pk": 77,
    "fields": {
      "username": "witherunicorn",
      "password": "TeWjXqJW3fV50VtNRlAhw0ntH2a8q7a8",
      "email": "witherunicorn@email.com",
      "is_superuser": false,
      "is_staff": false,
      "is_active": true,
      "date_joined": "1970-01-01 12:00:00.0+00:00"
    }
  },
  {
    "model": "auth.user",
    "pk": 78,
    "fields": {
      "username": "bacteriamushrooms",
      "password": "dCM02BrT2eBHvXO2QbCmcSvej9HrhJqX",
      "email": "bacteriamushrooms@email.com",
      "is_superuser": false,
      "is_staff": false,
      "is_active": true,
      "date_joined": "1970-01-01 12:00:00.0+00:00"
    }
  },
  {
    "model": "auth.user",
    "pk": 79,
    "fields": {
      "username": "averagereal",
      "password": "luMuxsM43GDfaKWkaRDYf03KlB8JRim4",
      "email": "averagereal@email.com",
      "is_superuser": false,
      "is_staff": false,
      "is_active": true,
      "date_joined": "1970-01-01 12:00:00.0+00:00"
    }
  },
  {
    "model": "auth.user",
    "pk": 80,
    "fields": {
      "username": "farmerclementine",
      "password": "TrEJJPeuFr42GyTvaf4BFvB16jq4YvKC",
      "email": "farmerclementine@email.com",
      "is_superuser": false,
      "is_staff": false,
      "is_active": true,
      "date_joined": "1970-01-01 12:00:00.0+00:00"
    }
  },
  {
    "model": "auth.user",
    "pk": 81,
    "fields": {
      "username": "dualshiver",
      "password": "KFvv9zews9gCOLHafJQjlOZC2rHiFr5d",
      "email": "dualshiver@email.com",
      "is_superuser": false,
      "is_staff": false,
      "is_active": true,
      "date_joined": "1970-01-01 12:00:00.0+00:00"
    }
  },
  {
    "model": "auth.user",
    "pk": 82,
    "fields": {
      "username": "leadershipwrithe",
      "password": "SpKX9gIYyi9AGoVRpZftABly1lNP94qE",
      "email": "leadershipwrithe@email.com",
      "is_superuser": false,
      "is_staff": false,
      "is_active": true,
      "date_joined": "1970-01-01 12:00:00.0+00:00"
    }
  },
  {
    "model": "auth.user",
    "pk": 83,
    "fields": {
      "username": "studaries",
      "password": "PX4mAP0SW3j0aZerZUq6UfMZFrzT7X7B",
      "email": "studaries@email.com",
      "is_superuser": false,
      "is_staff": false,
      "is_active": true,
      "date_joined": "1970-01-01 12:00:00.0+00:00"
    }
  },
  {
    "model": "auth.user",
    "pk": 84,
    "fields": {
      "username": "dustygood",
      "password": "g8JoJcjzKSQq3UjDrnwUTIX3c1tRTmKw",
      "email": "dustygood@email.com",
      "is_superuser": false,
      "is_staff": false,
      "is_active": true,
      "date_joined": "1970-01-01 12:00:00.0+00:00"
    }
  },
  {
    "model": "auth.user",
    "pk": 85,
    "fields": {
      "username": "straightappoint",
      "password": "6iSHmAoGGEglT6ym02mvGiOwgigR58Ql",
      "email": "straightappoint@email.com",
      "is_superuser": false,
      "is_staff": false,
      "is_active": true,
      "date_joined": "1970-01-01 12:00:00.0+00:00"
    }
  },
  {
    "model": "auth.user",
    "pk": 86,
    "fields": {
      "username": "foresaildiscourse",
      "password": "gR5epIH9i5AUX00tcrp4SVseFuKGNKN2",
      "email": "foresaildiscourse@email.com",
      "is_superuser": false,
      "is_staff": false,
      "is_active": true,
      "date_joined": "1970-01-01 12:00:00.0+00:00"
    }
  },
  {
    "model": "auth.user",
    "pk": 87,
    "fields": {
      "username": "billioneasily",
      "password": "REm2kJWugmKaTGqe98f2sDfCItvlW8Js",
      "email": "billioneasily@email.com",
      "is_superuser": false,
      "is_staff": false,
      "is_active": true,
      "date_joined": "1970-01-01 12:00:00.0+00:00"
    }
  },
  {
    "model": "auth.user",
    "pk": 88,
    "fields": {
      "username": "rowingmotherly",
      "password": "0v5ojVza8m3vLYwJTxRWvzIXN0rlcDvf",
      "email": "rowingmotherly@email.com",
      "is_superuser": false,
      "is_staff": false,
      "is_active": true,
      "date_joined": "1970-01-01 12:00:00.0+00:00"
    }
  },
  {
    "model": "auth.user",
    "pk": 89,
    "fields": {
      "username": "sweatpantssaving",
      "password": "bt706DnlOYR2hCjc6VitNhnvKmONWhVH",
      "email": "sweatpantssaving@email.com",
      "is_superuser": false,
      "is_staff": false,
      "is_active": true,
      "date_joined": "1970-01-01 12:00:00.0+00:00"
    }
  },
  {
    "model": "auth.user",
    "pk": 90,
    "fields": {
      "username": "longfeigned",
      "password": "0aQePhz9yjVz0xlACY6Etuv4Ada988BK",
      "email": "longfeigned@email.com",
      "is_superuser": false,
      "is_staff": false,
      "is_active": true,
      "date_joined": "1970-01-01 12:00:00.0+00:00"
    }
  },
  {
    "model": "auth.user",
    "pk": 91,
    "fields": {
      "username": "foxallianz",
      "password": "o7brf0YbNjLVmlYfkIheYfOClWoxLxnC",
      "email": "foxallianz@email.com",
      "is_superuser": false,
      "is_staff": false,
      "is_active": true,
      "date_joined": "1970-01-01 12:00:00.0+00:00"
    }
  },
  {
    "model": "auth.user",
    "pk": 92,
    "fields": {
      "username": "magpievisual",
      "password": "riAK4M93ywXWRLpmAKxVAmcEmQuq1Vjj",
      "email": "magpievisual@email.com",
      "is_superuser": false,
      "is_staff": false,
      "is_active": true,
      "date_joined": "1970-01-01 12:00:00.0+00:00"
    }
  },
  {
    "model": "auth.user",
    "pk": 93,
    "fields": {
      "username": "milescreech",
      "password": "9JnWRzZXTSvFgl0uGGtRegocyHNMUr8j",
      "email": "milescreech@email.com",
      "is_superuser": false,
      "is_staff": false,
      "is_active": true,
      "date_joined": "1970-01-01 12:00:00.0+00:00"
    }
  },
  {
    "model": "auth.user",
    "pk": 94,
    "fields": {
      "username": "mealynostalgic",
      "password": "OwvRl7fm0blgsfbL03rN9jbEvUEbtx1b",
      "email": "mealynostalgic@email.com",
      "is_superuser": false,
      "is_staff": false,
      "is_active": true,
      "date_joined": "1970-01-01 12:00:00.0+00:00"
    }
  },
  {
    "model": "auth.user",
    "pk": 95,
    "fields": {
      "username": "repaircommit",
      "password": "xT3mfnSFeA3vztKPWk3VwojdE2q5Xhle",
      "email": "repaircommit@email.com",
      "is_superuser": false,
      "is_staff": false,
      "is_active": true,
      "date_joined": "1970-01-01 12:00:00.0+00:00"
    }
  },
  {
    "model": "auth.user",
    "pk": 96,
    "fields": {
      "username": "stemsacred",
      "password": "CC1jevA1UBHWjjcBCApESPZFL8b5QnEF",
      "email": "stemsacred@email.com",
      "is_superuser": false,
      "is_staff": false,
      "is_active": true,
      "date_joined": "1970-01-01 12:00:00.0+00:00"
    }
  },
  {
    "model": "auth.user",
    "pk": 97,
    "fields": {
      "username": "asparagusintention",
      "password": "uzVpgeg3WxLDUUYXNGVhNprL2eNIApUj",
      "email": "asparagusintention@email.com",
      "is_superuser": false,
      "is_staff": false,
      "is_active": true,
      "date_joined": "1970-01-01 12:00:00.0+00:00"
    }
  },
  {
    "model": "auth.user",
    "pk": 98,
    "fields": {
      "username": "crickettaiga",
      "password": "iduOWaA9pfHambst7rAsqDpn1Tw7e3jD",
      "email": "crickettaiga@email.com",
      "is_superuser": false,
      "is_staff": false,
      "is_active": true,
      "date_joined": "1970-01-01 12:00:00.0+00:00"
    }
  },
  {
    "model": "auth.user",
    "pk": 99,
    "fields": {
      "username": "operatorassistance",
      "password": "vpDNJKx6lw5Z3jENkjuSW3mZseBW8IFY",
      "email": "operatorassistance@email.com",
      "is_superuser": false,
      "is_staff": false,
      "is_active": true,
      "date_joined": "1970-01-01 12:00:00.0+00:00"
    }
  },
  {
    "model": "auth.user",
    "pk": 100,
    "fields": {
      "username": "pillarpercentage",
      "password": "Q9ZanDZDqSjbVVD79YtJ008bGYS68eCg",
      "email": "pillarpercentage@email.com",
      "is_superuser": false,
      "is_staff": false,
      "is_active": true,
      "date_joined": "1970-01-01 12:00:00.0+00:00"
    }
  },
  {
    "model": "auth.user",
    "pk": 101,
    "fields": {
      "username": "journeymaple",
      "password": "ZPHyUvWyEvzDJW1r5tTm5CL0bfNClZZg",
      "email": "journeymaple@email.com",
      "is_superuser": false,
      "is_staff": false,
      "is_active": true,
      "date_joined": "1970-01-01 12:00:00.0+00:00"
    }
  },
  {
    "model": "auth.user",
    "pk": 102,
    "fields": {
      "username": "authorunsuitable",
      "password": "cxyxBP45BRVsyCzmPL7NyiJulQ9b4huK",
      "email": "authorunsuitable@email.com",
      "is_superuser": false,
      "is_staff": false,
      "is_active": true,
      "date_joined": "1970-01-01 12:00:00.0+00:00"
    }
  },
  {
    "model": "auth.user",
    "pk": 103,
    "fields": {
      "username": "sonmolt",
      "password": "6tsQOXnfesNQltHzVhU45hh1owXjmdTY",
      "email": "sonmolt@email.com",
      "is_superuser": false,
      "is_staff": false,
      "is_active": true,
      "date_joined": "1970-01-01 12:00:00.0+00:00"
    }
  },
  {
    "model": "auth.user",
    "pk": 104,
    "fields": {
      "username": "genuinefleet",
      "password": "d9RHvrfHHmObOhxI9UPo4zkXdfYkoYP2",
      "email": "genuinefleet@email.com",
      "is_superuser": false,
      "is_staff": false,
      "is_active": true,
      "date_joined": "1970-01-01 12:00:00.0+00:00"
    }
  },
  {
    "model": "auth.user",
    "pk": 105,
    "fields": {
      "username": "uncoveredvegan",
      "password": "B9q5NR3TwStWZm6ytaFIQBBIBYNms3XW",
      "email": "uncoveredvegan@email.com",
      "is_superuser": false,
      "is_staff": false,
      "is_active": true,
      "date_joined": "1970-01-01 12:00:00.0+00:00"
    }
  },
  {
    "model": "auth.user",
    "pk": 106,
    "fields": {
      "username": "sombrerohit",
      "password": "uQpZ9DJvVvTX9xlsPSKVbxqhxRzHOFk5",
      "email": "sombrerohit@email.com",
      "is_superuser": false,
      "is_staff": false,
      "is_active": true,
      "date_joined": "1970-01-01 12:00:00.0+00:00"
    }
  },
  {
    "model": "auth.user",
    "pk": 107,
    "fields": {
      "username": "confusedroll",
      "password": "vcg6hPZr0H2jaa0NZwi7QR0jUMaXejNe",
      "email": "confusedroll@email.com",
      "is_superuser": false,
      "is_staff": false,
      "is_active": true,
      "date_joined": "1970-01-01 12:00:00.0+00:00"
    }
  },
  {
    "model": "auth.user",
    "pk": 108,
    "fields": {
      "username": "jokerunlock",
      "password": "R3Zz2UR5ipfOqDTcYGCDrT6mmvRTawC4",
      "email": "jokerunlock@email.com",
      "is_superuser": false,
      "is_staff": false,
      "is_active": true,
      "date_joined": "1970-01-01 12:00:00.0+00:00"
    }
  },
  {
    "model": "auth.user",
    "pk": 109,
    "fields": {
      "username": "barterhonk",
      "password": "OTp7lsfIjg6gKLcaywxLVAHjwvGxB6WZ",
      "email": "barterhonk@email.com",
      "is_superuser": false,
      "is_staff": false,
      "is_active": true,
      "date_joined": "1970-01-01 12:00:00.0+00:00"
    }
  },
  {
    "model": "auth.user",
    "pk": 110,
    "fields": {
      "username": "analysispurse",
      "password": "H8SEGRBoXqUOfI9oH08hJlnLiUpRDPIz",
      "email": "analysispurse@email.com",
      "is_superuser": false,
      "is_staff": false,
      "is_active": true,
      "date_joined": "1970-01-01 12:00:00.0+00:00"
    }
  },
  {
    "model": "auth.user",
    "pk": 111,
    "fields": {
      "username": "amazedemployee",
      "password": "DlEsJ4RqHQQPI6OW7KwxqopaykgYQa2p",
      "email": "amazedemployee@email.com",
      "is_superuser": false,
      "is_staff": false,
      "is_active": true,
      "date_joined": "1970-01-01 12:00:00.0+00:00"
    }
  },
  {
    "model": "auth.user",
    "pk": 112,
    "fields": {
      "username": "lividactivator",
      "password": "7fNjlXrNwWgOkAJNhHve7E5fqs63W9U6",
      "email": "lividactivator@email.com",
      "is_superuser": false,
      "is_staff": false,
      "is_active": true,
      "date_joined": "1970-01-01 12:00:00.0+00:00"
    }
  },
  {
    "model": "auth.user",
    "pk": 113,
    "fields": {
      "username": "advancedmicrosoft",
      "password": "tc1mhc0rTPJ2sRyexOdk7Sk0ulNEn1vc",
      "email": "advancedmicrosoft@email.com",
      "is_superuser": false,
      "is_staff": false,
      "is_active": true,
      "date_joined": "1970-01-01 12:00:00.0+00:00"
    }
  },
  {
    "model": "auth.user",
    "pk": 114,
    "fields": {
      "username": "teencrucial",
      "password": "JLXD2ZUTYIoOM6gyPZ2w59xEprA0t2y0",
      "email": "teencrucial@email.com",
      "is_superuser": false,
      "is_staff": false,
      "is_active": true,
      "date_joined": "1970-01-01 12:00:00.0+00:00"
    }
  },
  {
    "model": "auth.user",
    "pk": 115,
    "fields": {
      "username": "musselspenitent",
      "password": "gSug5gBKLrTku7t1mgI0pm0qCb7U8fPe",
      "email": "musselspenitent@email.com",
      "is_superuser": false,
      "is_staff": false,
      "is_active": true,
      "date_joined": "1970-01-01 12:00:00.0+00:00"
    }
  },
  {
    "model": "auth.user",
    "pk": 116,
    "fields": {
      "username": "frapshepherd",
      "password": "R9zPZApkQLRThU4pcMOLKZnd7twSj3O5",
      "email": "frapshepherd@email.com",
      "is_superuser": false,
      "is_staff": false,
      "is_active": true,
      "date_joined": "1970-01-01 12:00:00.0+00:00"
    }
  },
  {
    "model": "auth.user",
    "pk": 117,
    "fields": {
      "username": "riptideuneven",
      "password": "DWZS53VgA1UgfblZZHiLd0YNjAoH5jzq",
      "email": "riptideuneven@email.com",
      "is_superuser": false,
      "is_staff": false,
      "is_active": true,
      "date_joined": "1970-01-01 12:00:00.0+00:00"
    }
  },
  {
    "model": "auth.user",
    "pk": 118,
    "fields": {
      "username": "presidentphysician",
      "password": "83q7KWtiw8tJAvktVLrvIcrCBwVnP9DU",
      "email": "presidentphysician@email.com",
      "is_superuser": false,
      "is_staff": false,
      "is_active": true,
      "date_joined": "1970-01-01 12:00:00.0+00:00"
    }
  },
  {
    "model": "auth.user",
    "pk": 119,
    "fields": {
      "username": "jarmeasure",
      "password": "V7QTTx4GfMc3xhIDVSY5GHvNTpBQxDAy",
      "email": "jarmeasure@email.com",
      "is_superuser": false,
      "is_staff": false,
      "is_active": true,
      "date_joined": "1970-01-01 12:00:00.0+00:00"
    }
  },
  {
    "model": "auth.user",
    "pk": 120,
    "fields": {
      "username": "totalcoral",
      "password": "Kt4XzMW05Zui8Vsz351vKLJjxbeeQri5",
      "email": "totalcoral@email.com",
      "is_superuser": false,
      "is_staff": false,
      "is_active": true,
      "date_joined": "1970-01-01 12:00:00.0+00:00"
    }
  },
  {
    "model": "auth.user",
    "pk": 121,
    "fields": {
      "username": "blindmemorable",
      "password": "9pAhNZLKOTLlj9N2KidDB0ATrN8FvufQ",
      "email": "blindmemorable@email.com",
      "is_superuser": false,
      "is_staff": false,
      "is_active": true,
      "date_joined": "1970-01-01 12:00:00.0+00:00"
    }
  },
  {
    "model": "auth.user",
    "pk": 122,
    "fields": {
      "username": "ceilingpunch",
      "password": "8Glwa3K04oyqSzqQRas3R6guaNK5Kmmu",
      "email": "ceilingpunch@email.com",
      "is_superuser": false,
      "is_staff": false,
      "is_active": true,
      "date_joined": "1970-01-01 12:00:00.0+00:00"
    }
  },
  {
    "model": "auth.user",
    "pk": 123,
    "fields": {
      "username": "adviceadamant",
      "password": "jWvTjrtQaZFCMmoJyPfNfSLhDWUG1qY8",
      "email": "adviceadamant@email.com",
      "is_superuser": false,
      "is_staff": false,
      "is_active": true,
      "date_joined": "1970-01-01 12:00:00.0+00:00"
    }
  },
  {
    "model": "auth.user",
    "pk": 124,
    "fields": {
      "username": "postboxstone",
      "password": "2WFlBWcUGPiZOffI1MYbM4B5U7tPD6BW",
      "email": "postboxstone@email.com",
      "is_superuser": false,
      "is_staff": false,
      "is_active": true,
      "date_joined": "1970-01-01 12:00:00.0+00:00"
    }
  },
  {
    "model": "auth.user",
    "pk": 125,
    "fields": {
      "username": "podblare",
      "password": "x7I40dHuab5zqeV5JOSfzBLwMjqwPrcl",
      "email": "podblare@email.com",
      "is_superuser": false,
      "is_staff": false,
      "is_active": true,
      "date_joined": "1970-01-01 12:00:00.0+00:00"
    }
  },
  {
    "model": "auth.user",
    "pk": 126,
    "fields": {
      "username": "luresloth",
      "password": "Sxq3EYF3eHb1fZymJ8hXkNouS3aSDJNa",
      "email": "luresloth@email.com",
      "is_superuser": false,
      "is_staff": false,
      "is_active": true,
      "date_joined": "1970-01-01 12:00:00.0+00:00"
    }
  },
  {
    "model": "auth.user",
    "pk": 127,
    "fields": {
      "username": "flairheadproductive",
      "password": "p49rYvcIjGeWvBPQqGKrcozTU4l0MaEH",
      "email": "flairheadproductive@email.com",
      "is_superuser": false,
      "is_staff": false,
      "is_active": true,
      "date_joined": "1970-01-01 12:00:00.0+00:00"
    }
  },
  {
    "model": "auth.user",
    "pk": 128,
    "fields": {
      "username": "skycharming",
      "password": "UywzqfKukq7n1cLSHfWXcSiGm6PzFIVG",
      "email": "skycharming@email.com",
      "is_superuser": false,
      "is_staff": false,
      "is_active": true,
      "date_joined": "1970-01-01 12:00:00.0+00:00"
    }
  },
  {
    "model": "auth.user",
    "pk": 129,
    "fields": {
      "username": "microbetrifling",
      "password": "zjGVa960Vxx3SDsFgyh2Z2GD4mnnTHQ2",
      "email": "microbetrifling@email.com",
      "is_superuser": false,
      "is_staff": false,
      "is_active": true,
      "date_joined": "1970-01-01 12:00:00.0+00:00"
    }
  },
  {
    "model": "auth.user",
    "pk": 130,
    "fields": {
      "username": "whoseviolation",
      "password": "IXIrY3elqjfElSnT1T1hZV9F29ZmJsJG",
      "email": "whoseviolation@email.com",
      "is_superuser": false,
      "is_staff": false,
      "is_active": true,
      "date_joined": "1970-01-01 12:00:00.0+00:00"
    }
  },
  {
    "model": "auth.user",
    "pk": 131,
    "fields": {
      "username": "crushingcustom",
      "password": "froFVc9nlgJRo63pujhKrB63cURCDR0E",
      "email": "crushingcustom@email.com",
      "is_superuser": false,
      "is_staff": false,
      "is_active": true,
      "date_joined": "1970-01-01 12:00:00.0+00:00"
    }
  },
  {
    "model": "auth.user",
    "pk": 132,
    "fields": {
      "username": "behaveentrance",
      "password": "Z3oWucboZLYLxl6yYUGQsPEd8cr489WI",
      "email": "behaveentrance@email.com",
      "is_superuser": false,
      "is_staff": false,
      "is_active": true,
      "date_joined": "1970-01-01 12:00:00.0+00:00"
    }
  },
  {
    "model": "auth.user",
    "pk": 133,
    "fields": {
      "username": "batterynod",
      "password": "G7qufwM3jyFqEmh760NKyEqBRMvnW23n",
      "email": "batterynod@email.com",
      "is_superuser": false,
      "is_staff": false,
      "is_active": true,
      "date_joined": "1970-01-01 12:00:00.0+00:00"
    }
  },
  {
    "model": "auth.user",
    "pk": 134,
    "fields": {
      "username": "grocerymove",
      "password": "qWpNhXstp3gGzgpLbklJ3X2cF08vLNZ3",
      "email": "grocerymove@email.com",
      "is_superuser": false,
      "is_staff": false,
      "is_active": true,
      "date_joined": "1970-01-01 12:00:00.0+00:00"
    }
  },
  {
    "model": "auth.user",
    "pk": 135,
    "fields": {
      "username": "bluetvillager",
      "password": "R8suCaZ9vJ6UjEBdYNoJyazTw5ziKr3K",
      "email": "bluetvillager@email.com",
      "is_superuser": false,
      "is_staff": false,
      "is_active": true,
      "date_joined": "1970-01-01 12:00:00.0+00:00"
    }
  },
  {
    "model": "auth.user",
    "pk": 136,
    "fields": {
      "username": "cherryxmas",
      "password": "Kew9P9bKbl5FJvtchq42eVV6AhDBlKWU",
      "email": "cherryxmas@email.com",
      "is_superuser": false,
      "is_staff": false,
      "is_active": true,
      "date_joined": "1970-01-01 12:00:00.0+00:00"
    }
  },
  {
    "model": "auth.user",
    "pk": 137,
    "fields": {
      "username": "basisnoun",
      "password": "EvyES9cJS1twcujava8BpTzybRm2nSZn",
      "email": "basisnoun@email.com",
      "is_superuser": false,
      "is_staff": false,
      "is_active": true,
      "date_joined": "1970-01-01 12:00:00.0+00:00"
    }
  },
  {
    "model": "auth.user",
    "pk": 138,
    "fields": {
      "username": "artificialquaint",
      "password": "NYOqgN0kk4HYOv8UDM9WlQMvuZAfucS3",
      "email": "artificialquaint@email.com",
      "is_superuser": false,
      "is_staff": false,
      "is_active": true,
      "date_joined": "1970-01-01 12:00:00.0+00:00"
    }
  },
  {
    "model": "auth.user",
    "pk": 139,
    "fields": {
      "username": "reliablefletching",
      "password": "vv2F7VBEmF0LyAVLHJBqLgGOY7fB1P89",
      "email": "reliablefletching@email.com",
      "is_superuser": false,
      "is_staff": false,
      "is_active": true,
      "date_joined": "1970-01-01 12:00:00.0+00:00"
    }
  },
  {
    "model": "auth.user",
    "pk": 140,
    "fields": {
      "username": "exultantleotard",
      "password": "vY6QKaMpWCdOTFPLf4PpAjMCSYJiuTKU",
      "email": "exultantleotard@email.com",
      "is_superuser": false,
      "is_staff": false,
      "is_active": true,
      "date_joined": "1970-01-01 12:00:00.0+00:00"
    }
  },
  {
    "model": "auth.user",
    "pk": 141,
    "fields": {
      "username": "admitgecko",
      "password": "aoO6xTlLhCNrO9eCBvJ28c9kXg9ogPmU",
      "email": "admitgecko@email.com",
      "is_superuser": false,
      "is_staff": false,
      "is_active": true,
      "date_joined": "1970-01-01 12:00:00.0+00:00"
    }
  },
  {
    "model": "auth.user",
    "pk": 142,
    "fields": {
      "username": "pebblefurniture",
      "password": "sCU8y0txOsf1WmcOzletbZ7j23yZeoFO",
      "email": "pebblefurniture@email.com",
      "is_superuser": false,
      "is_staff": false,
      "is_active": true,
      "date_joined": "1970-01-01 12:00:00.0+00:00"
    }
  },
  {
    "model": "auth.user",
    "pk": 143,
    "fields": {
      "username": "turbanabsorbing",
      "password": "GdYFk3Vz6vchpjRkBmFdauMBRNbGhald",
      "email": "turbanabsorbing@email.com",
      "is_superuser": false,
      "is_staff": false,
      "is_active": true,
      "date_joined": "1970-01-01 12:00:00.0+00:00"
    }
  },
  {
    "model": "auth.user",
    "pk": 144,
    "fields": {
      "username": "sodahandball",
      "password": "Wiif7DZOBoW9LrN9PsquZqpBYHBGXFnj",
      "email": "sodahandball@email.com",
      "is_superuser": false,
      "is_staff": false,
      "is_active": true,
      "date_joined": "1970-01-01 12:00:00.0+00:00"
    }
  },
  {
    "model": "auth.user",
    "pk": 145,
    "fields": {
      "username": "joystickhis",
      "password": "6cgzBwguoKpj0ehjeH2MoXKddoWfY65R",
      "email": "joystickhis@email.com",
      "is_superuser": false,
      "is_staff": false,
      "is_active": true,
      "date_joined": "1970-01-01 12:00:00.0+00:00"
    }
  },
  {
    "model": "auth.user",
    "pk": 146,
    "fields": {
      "username": "gybebloated",
      "password": "u1yNNAcIJIFnU9Ufcsg5BWJp1Inn4rJb",
      "email": "gybebloated@email.com",
      "is_superuser": false,
      "is_staff": false,
      "is_active": true,
      "date_joined": "1970-01-01 12:00:00.0+00:00"
    }
  },
  {
    "model": "auth.user",
    "pk": 147,
    "fields": {
      "username": "hornbillesteemed",
      "password": "sv2UX1mjoojHbjpWRNzisP32fVMvB99j",
      "email": "hornbillesteemed@email.com",
      "is_superuser": false,
      "is_staff": false,
      "is_active": true,
      "date_joined": "1970-01-01 12:00:00.0+00:00"
    }
  },
  {
    "model": "auth.user",
    "pk": 148,
    "fields": {
      "username": "posemash",
      "password": "VmwNguKztmaDOcSLUgFo72SJM57fhNgW",
      "email": "posemash@email.com",
      "is_superuser": false,
      "is_staff": false,
      "is_active": true,
      "date_joined": "1970-01-01 12:00:00.0+00:00"
    }
  },
  {
    "model": "auth.user",
    "pk": 149,
    "fields": {
      "username": "labourergroup",
      "password": "LkVSJ14dNwGAAeyFHmMhoHmd0wB36hCA",
      "email": "labourergroup@email.com",
      "is_superuser": false,
      "is_staff": false,
      "is_active": true,
      "date_joined": "1970-01-01 12:00:00.0+00:00"
    }
  },
  {
    "model": "auth.user",
    "pk": 150,
    "fields": {
      "username": "mansionmeet",
      "password": "ic1dShY1PWDKeaM262rlWQAMFnw5fORd",
      "email": "mansionmeet@email.com",
      "is_superuser": false,
      "is_staff": false,
      "is_active": true,
      "date_joined": "1970-01-01 12:00:00.0+00:00"
    }
  },
  {
    "model": "auth.user",
    "pk": 151,
    "fields": {
      "username": "mixautomobile",
      "password": "dVI3fyYLJmekxUbyiJOUl5Ti2XgjefWt",
      "email": "mixautomobile@email.com",
      "is_superuser": false,
      "is_staff": false,
      "is_active": true,
      "date_joined": "1970-01-01 12:00:00.0+00:00"
    }
  },
  {
    "model": "auth.user",
    "pk": 152,
    "fields": {
      "username": "daggerpeaches",
      "password": "A1zMuvIlLfj53NaR5EqE6dYOVPvfraUQ",
      "email": "daggerpeaches@email.com",
      "is_superuser": false,
      "is_staff": false,
      "is_active": true,
      "date_joined": "1970-01-01 12:00:00.0+00:00"
    }
  },
  {
    "model": "auth.user",
    "pk": 153,
    "fields": {
      "username": "swimfar",
      "password": "G55drBB1RGh6ZdYet4bWjxi3TeefiSjG",
      "email": "swimfar@email.com",
      "is_superuser": false,
      "is_staff": false,
      "is_active": true,
      "date_joined": "1970-01-01 12:00:00.0+00:00"
    }
  },
  {
    "model": "auth.user",
    "pk": 154,
    "fields": {
      "username": "handyescutcheon",
      "password": "GjMGAZP24Nun24xmT5MO69gI6IDwYN5r",
      "email": "handyescutcheon@email.com",
      "is_superuser": false,
      "is_staff": false,
      "is_active": true,
      "date_joined": "1970-01-01 12:00:00.0+00:00"
    }
  },
  {
    "model": "auth.user",
    "pk": 155,
    "fields": {
      "username": "unpopularstorm",
      "password": "nK6jPw0pWYVLoEDRyRM1XSxkThVRAPlH",
      "email": "unpopularstorm@email.com",
      "is_superuser": false,
      "is_staff": false,
      "is_active": true,
      "date_joined": "1970-01-01 12:00:00.0+00:00"
    }
  },
  {
    "model": "auth.user",
    "pk": 156,
    "fields": {
      "username": "stopsmoked",
      "password": "PQKB9anizg0jZ2jnp646FpMudCOrzizq",
      "email": "stopsmoked@email.com",
      "is_superuser": false,
      "is_staff": false,
      "is_active": true,
      "date_joined": "1970-01-01 12:00:00.0+00:00"
    }
  },
  {
    "model": "auth.user",
    "pk": 157,
    "fields": {
      "username": "extolllastage",
      "password": "GJg7ThfTFBZFKLwkXuG9vvE9RHcAxsRs",
      "email": "extolllastage@email.com",
      "is_superuser": false,
      "is_staff": false,
      "is_active": true,
      "date_joined": "1970-01-01 12:00:00.0+00:00"
    }
  },
  {
    "model": "auth.user",
    "pk": 158,
    "fields": {
      "username": "lateenlymph",
      "password": "7SJzSzLO4dW9A0zfN8iF8F2G77IE4ZIU",
      "email": "lateenlymph@email.com",
      "is_superuser": false,
      "is_staff": false,
      "is_active": true,
      "date_joined": "1970-01-01 12:00:00.0+00:00"
    }
  },
  {
    "model": "auth.user",
    "pk": 159,
    "fields": {
      "username": "candycanebiscay",
      "password": "GAysuecs046COJWqYIkyBffcJEfkeEne",
      "email": "candycanebiscay@email.com",
      "is_superuser": false,
      "is_staff": false,
      "is_active": true,
      "date_joined": "1970-01-01 12:00:00.0+00:00"
    }
  },
  {
    "model": "auth.user",
    "pk": 160,
    "fields": {
      "username": "arroganttroubled",
      "password": "hEf3g9SkofYhNH5dZScp1XomcrFiDtkN",
      "email": "arroganttroubled@email.com",
      "is_superuser": false,
      "is_staff": false,
      "is_active": true,
      "date_joined": "1970-01-01 12:00:00.0+00:00"
    }
  },
  {
    "model": "auth.user",
    "pk": 161,
    "fields": {
      "username": "littlecloak",
      "password": "CDNwBoZgoMA2sAHDVmG2TOeVvKBRFFSb",
      "email": "littlecloak@email.com",
      "is_superuser": false,
      "is_staff": false,
      "is_active": true,
      "date_joined": "1970-01-01 12:00:00.0+00:00"
    }
  },
  {
    "model": "auth.user",
    "pk": 162,
    "fields": {
      "username": "condemnedaudience",
      "password": "FsMUNSsIjISWSOwa2vvfQxZPhCkq9GQs",
      "email": "condemnedaudience@email.com",
      "is_superuser": false,
      "is_staff": false,
      "is_active": true,
      "date_joined": "1970-01-01 12:00:00.0+00:00"
    }
  },
  {
    "model": "auth.user",
    "pk": 163,
    "fields": {
      "username": "cheerfulphysical",
      "password": "2HV4Z2etHUMhzaWvlwufavCAYeCwWe1z",
      "email": "cheerfulphysical@email.com",
      "is_superuser": false,
      "is_staff": false,
      "is_active": true,
      "date_joined": "1970-01-01 12:00:00.0+00:00"
    }
  },
  {
    "model": "auth.user",
    "pk": 164,
    "fields": {
      "username": "lastingmedia",
      "password": "uwhjWmERqB6hTDiAbyzkN6ksttkR8g9Q",
      "email": "lastingmedia@email.com",
      "is_superuser": false,
      "is_staff": false,
      "is_active": true,
      "date_joined": "1970-01-01 12:00:00.0+00:00"
    }
  },
  {
    "model": "auth.user",
    "pk": 165,
    "fields": {
      "username": "moaningenglish",
      "password": "MRXQ3UcOtMLlUpj8c5ObkEU5oz2CiVHN",
      "email": "moaningenglish@email.com",
      "is_superuser": false,
      "is_staff": false,
      "is_active": true,
      "date_joined": "1970-01-01 12:00:00.0+00:00"
    }
  },
  {
    "model": "auth.user",
    "pk": 166,
    "fields": {
      "username": "shortstopmean",
      "password": "C0B0IvkB5Ql8XYw4TLs6n7aBreEQc816",
      "email": "shortstopmean@email.com",
      "is_superuser": false,
      "is_staff": false,
      "is_active": true,
      "date_joined": "1970-01-01 12:00:00.0+00:00"
    }
  },
  {
    "model": "auth.user",
    "pk": 167,
    "fields": {
      "username": "willowbasis",
      "password": "WfmtAWMFWc99MABaHhwWxSeyab85ykXR",
      "email": "willowbasis@email.com",
      "is_superuser": false,
      "is_staff": false,
      "is_active": true,
      "date_joined": "1970-01-01 12:00:00.0+00:00"
    }
  },
  {
    "model": "auth.user",
    "pk": 168,
    "fields": {
      "username": "roachguillemot",
      "password": "qbXPyBgmGeNNkoBAOGmEHdhFmAdKG25n",
      "email": "roachguillemot@email.com",
      "is_superuser": false,
      "is_staff": false,
      "is_active": true,
      "date_joined": "1970-01-01 12:00:00.0+00:00"
    }
  },
  {
    "model": "auth.user",
    "pk": 169,
    "fields": {
      "username": "inviteacquire",
      "password": "SQGi10PIj3MAqfCDEOGZPzisKaPU1IZe",
      "email": "inviteacquire@email.com",
      "is_superuser": false,
      "is_staff": false,
      "is_active": true,
      "date_joined": "1970-01-01 12:00:00.0+00:00"
    }
  },
  {
    "model": "auth.user",
    "pk": 170,
    "fields": {
      "username": "wealthymyth",
      "password": "ssYuZtT7u8vR5NclpTOsFIkl88AoVUkj",
      "email": "wealthymyth@email.com",
      "is_superuser": false,
      "is_staff": false,
      "is_active": true,
      "date_joined": "1970-01-01 12:00:00.0+00:00"
    }
  },
  {
    "model": "auth.user",
    "pk": 171,
    "fields": {
      "username": "coaloreaquatic",
      "password": "dPsVEPa3Z1BdXNghGpt5EJ94gTQx9gTE",
      "email": "coaloreaquatic@email.com",
      "is_superuser": false,
      "is_staff": false,
      "is_active": true,
      "date_joined": "1970-01-01 12:00:00.0+00:00"
    }
  },
  {
    "model": "auth.user",
    "pk": 172,
    "fields": {
      "username": "involvedstrike",
      "password": "ur1MDcQOJhYx4SjAwmMQmdwqGLYJeKR5",
      "email": "involvedstrike@email.com",
      "is_superuser": false,
      "is_staff": false,
      "is_active": true,
      "date_joined": "1970-01-01 12:00:00.0+00:00"
    }
  },
  {
    "model": "auth.user",
    "pk": 173,
    "fields": {
      "username": "endcitytwin",
      "password": "5AolhQEP0QWoX6zdK0998EXp4bHtMKzq",
      "email": "endcitytwin@email.com",
      "is_superuser": false,
      "is_staff": false,
      "is_active": true,
      "date_joined": "1970-01-01 12:00:00.0+00:00"
    }
  },
  {
    "model": "auth.user",
    "pk": 174,
    "fields": {
      "username": "crabbyfortunate",
      "password": "L854aLlFyuGNG4BBECeGELNXpUBehcAw",
      "email": "crabbyfortunate@email.com",
      "is_superuser": false,
      "is_staff": false,
      "is_active": true,
      "date_joined": "1970-01-01 12:00:00.0+00:00"
    }
  },
  {
    "model": "auth.user",
    "pk": 175,
    "fields": {
      "username": "pansyprove",
      "password": "EQvjFaP1o8KgVUfNt85cTQd8KlxwnbeA",
      "email": "pansyprove@email.com",
      "is_superuser": false,
      "is_staff": false,
      "is_active": true,
      "date_joined": "1970-01-01 12:00:00.0+00:00"
    }
  },
  {
    "model": "auth.user",
    "pk": 176,
    "fields": {
      "username": "earningspick",
      "password": "vLiyikpMegU6qRkg9s9iaeJXLal1Dsq9",
      "email": "earningspick@email.com",
      "is_superuser": false,
      "is_staff": false,
      "is_active": true,
      "date_joined": "1970-01-01 12:00:00.0+00:00"
    }
  },
  {
    "model": "auth.user",
    "pk": 177,
    "fields": {
      "username": "withscuttles",
      "password": "AMJxjVJfltRYZUFs8Kj66tC48uwJbH8w",
      "email": "withscuttles@email.com",
      "is_superuser": false,
      "is_staff": false,
      "is_active": true,
      "date_joined": "1970-01-01 12:00:00.0+00:00"
    }
  },
  {
    "model": "auth.user",
    "pk": 178,
    "fields": {
      "username": "clausconnect",
      "password": "noNRc5dU3DCjf5x5L1cboKuyMABoeWJ7",
      "email": "clausconnect@email.com",
      "is_superuser": false,
      "is_staff": false,
      "is_active": true,
      "date_joined": "1970-01-01 12:00:00.0+00:00"
    }
  },
  {
    "model": "auth.user",
    "pk": 179,
    "fields": {
      "username": "learnedinborn",
      "password": "6lG2Ls5pSmSA4E8DiTlnp1LTMfh7l8Xs",
      "email": "learnedinborn@email.com",
      "is_superuser": false,
      "is_staff": false,
      "is_active": true,
      "date_joined": "1970-01-01 12:00:00.0+00:00"
    }
  },
  {
    "model": "auth.user",
    "pk": 180,
    "fields": {
      "username": "welltodofez",
      "password": "abM7hrxQPppwv0YNSPZsprxwuWisNuYF",
      "email": "welltodofez@email.com",
      "is_superuser": false,
      "is_staff": false,
      "is_active": true,
      "date_joined": "1970-01-01 12:00:00.0+00:00"
    }
  },
  {
    "model": "auth.user",
    "pk": 181,
    "fields": {
      "username": "dieticianexamine",
      "password": "ArIDiUH1jIDpKDbiAzMgu7j0l7FFyAIy",
      "email": "dieticianexamine@email.com",
      "is_superuser": false,
      "is_staff": false,
      "is_active": true,
      "date_joined": "1970-01-01 12:00:00.0+00:00"
    }
  },
  {
    "model": "auth.user",
    "pk": 182,
    "fields": {
      "username": "needsizzle",
      "password": "FfuVpYIsxO00h9wClbBImHLrVu1Rq9GC",
      "email": "needsizzle@email.com",
      "is_superuser": false,
      "is_staff": false,
      "is_active": true,
      "date_joined": "1970-01-01 12:00:00.0+00:00"
    }
  },
  {
    "model": "auth.user",
    "pk": 183,
    "fields": {
      "username": "flowerpothappy",
      "password": "jInjsQjsw3DWkFJRawTuSIa7A6lXoe0u",
      "email": "flowerpothappy@email.com",
      "is_superuser": false,
      "is_staff": false,
      "is_active": true,
      "date_joined": "1970-01-01 12:00:00.0+00:00"
    }
  },
  {
    "model": "auth.user",
    "pk": 184,
    "fields": {
      "username": "mediumreligion",
      "password": "CL13sPCb8tA7DlN8QdAus081kBXZZpAk",
      "email": "mediumreligion@email.com",
      "is_superuser": false,
      "is_staff": false,
      "is_active": true,
      "date_joined": "1970-01-01 12:00:00.0+00:00"
    }
  },
  {
    "model": "auth.user",
    "pk": 185,
    "fields": {
      "username": "fibulaapathetic",
      "password": "SYYUiaYCNOm4eYS3oK0If86yfKg7HTKH",
      "email": "fibulaapathetic@email.com",
      "is_superuser": false,
      "is_staff": false,
      "is_active": true,
      "date_joined": "1970-01-01 12:00:00.0+00:00"
    }
  },
  {
    "model": "auth.user",
    "pk": 186,
    "fields": {
      "username": "robinpharmacist",
      "password": "oEYLwzw8Hqz1xvyT7WoG1leXJKi33mSY",
      "email": "robinpharmacist@email.com",
      "is_superuser": false,
      "is_staff": false,
      "is_active": true,
      "date_joined": "1970-01-01 12:00:00.0+00:00"
    }
  },
  {
    "model": "auth.user",
    "pk": 187,
    "fields": {
      "username": "mayorbricks",
      "password": "87TnvFpvXFpYDJXxY414m4K6IzgFVJxA",
      "email": "mayorbricks@email.com",
      "is_superuser": false,
      "is_staff": false,
      "is_active": true,
      "date_joined": "1970-01-01 12:00:00.0+00:00"
    }
  },
  {
    "model": "auth.user",
    "pk": 188,
    "fields": {
      "username": "hoveritch",
      "password": "DfvP6B3HeUCG7LjcZGQPwB2QkdyVpweh",
      "email": "hoveritch@email.com",
      "is_superuser": false,
      "is_staff": false,
      "is_active": true,
      "date_joined": "1970-01-01 12:00:00.0+00:00"
    }
  },
  {
    "model": "auth.user",
    "pk": 189,
    "fields": {
      "username": "staffusual",
      "password": "jO16fc1YdyMMwOjxSEDONBB6t6k9NiAJ",
      "email": "staffusual@email.com",
      "is_superuser": false,
      "is_staff": false,
      "is_active": true,
      "date_joined": "1970-01-01 12:00:00.0+00:00"
    }
  },
  {
    "model": "auth.user",
    "pk": 190,
    "fields": {
      "username": "imaginarypretzel",
      "password": "SfKpzJUMTluDVGna4oqZihQ8x2KDmitr",
      "email": "imaginarypretzel@email.com",
      "is_superuser": false,
      "is_staff": false,
      "is_active": true,
      "date_joined": "1970-01-01 12:00:00.0+00:00"
    }
  },
  {
    "model": "auth.user",
    "pk": 191,
    "fields": {
      "username": "visibilitysponson",
      "password": "w0hvYuTtSRq93CMirkBWJ2hmYBTQtZMu",
      "email": "visibilitysponson@email.com",
      "is_superuser": false,
      "is_staff": false,
      "is_active": true,
      "date_joined": "1970-01-01 12:00:00.0+00:00"
    }
  },
  {
    "model": "auth.user",
    "pk": 192,
    "fields": {
      "username": "flipflopsnursery",
      "password": "Lx8oLQ9gUrYzWJKhyDBgCiUTX2qfjgNt",
      "email": "flipflopsnursery@email.com",
      "is_superuser": false,
      "is_staff": false,
      "is_active": true,
      "date_joined": "1970-01-01 12:00:00.0+00:00"
    }
  },
  {
    "model": "auth.user",
    "pk": 193,
    "fields": {
      "username": "illustrategripping",
      "password": "CBW17eAl5dkG58jF8JVhsJ8BehRKOSBF",
      "email": "illustrategripping@email.com",
      "is_superuser": false,
      "is_staff": false,
      "is_active": true,
      "date_joined": "1970-01-01 12:00:00.0+00:00"
    }
  },
  {
    "model": "auth.user",
    "pk": 194,
    "fields": {
      "username": "teargiving",
      "password": "Gj1fWYZ57W9OualbOEHPRFfEjjzgsRIf",
      "email": "teargiving@email.com",
      "is_superuser": false,
      "is_staff": false,
      "is_active": true,
      "date_joined": "1970-01-01 12:00:00.0+00:00"
    }
  },
  {
    "model": "auth.user",
    "pk": 195,
    "fields": {
      "username": "essexpacked",
      "password": "2mUtzJYjf4ag8SHTBlLe8opUnmEAqohh",
      "email": "essexpacked@email.com",
      "is_superuser": false,
      "is_staff": false,
      "is_active": true,
      "date_joined": "1970-01-01 12:00:00.0+00:00"
    }
  },
  {
    "model": "auth.user",
    "pk": 196,
    "fields": {
      "username": "overdueglasses",
      "password": "gwofK4bWgvPCUkvFBo9qGXIjDmuFFMLB",
      "email": "overdueglasses@email.com",
      "is_superuser": false,
      "is_staff": false,
      "is_active": true,
      "date_joined": "1970-01-01 12:00:00.0+00:00"
    }
  },
  {
    "model": "auth.user",
    "pk": 197,
    "fields": {
      "username": "rainytaste",
      "password": "KTPOVBEzsaOTciEBGB8dvIbZKf6UfM04",
      "email": "rainytaste@email.com",
      "is_superuser": false,
      "is_staff": false,
      "is_active": true,
      "date_joined": "1970-01-01 12:00:00.0+00:00"
    }
  },
  {
    "model": "auth.user",
    "pk": 198,
    "fields": {
      "username": "herbnothing",
      "password": "zE38nR4qWdQBWFexpu3d8OimidRApUqr",
      "email": "herbnothing@email.com",
      "is_superuser": false,
      "is_staff": false,
      "is_active": true,
      "date_joined": "1970-01-01 12:00:00.0+00:00"
    }
  },
  {
    "model": "auth.user",
    "pk": 199,
    "fields": {
      "username": "crochetmaniacal",
      "password": "3HaWbw2P1gEPOM2rWPWwaYMgmspo9tPr",
      "email": "crochetmaniacal@email.com",
      "is_superuser": false,
      "is_staff": false,
      "is_active": true,
      "date_joined": "1970-01-01 12:00:00.0+00:00"
    }
  },
  {
    "model": "auth.user",
    "pk": 200,
    "fields": {
      "username": "congresshabitat",
      "password": "nMUpT9T90CP9jQx1yRqHjcdeX5bS7LWW",
      "email": "congresshabitat@email.com",
      "is_superuser": false,
      "is_staff": false,
      "is_active": true,
      "date_joined": "1970-01-01 12:00:00.0+00:00"
    }
  },
  {
    "model": "auth.user",
    "pk": 201,
    "fields": {
      "username": "overworlddemonic",
      "password": "kfmcPiLdILAWDdL4VV2hNWhVoMGWCz9h",
      "email": "overworlddemonic@email.com",
      "is_superuser": false,
      "is_staff": false,
      "is_active": true,
      "date_joined": "1970-01-01 12:00:00.0+00:00"
    }
  }
]
